{
  "as_of": "2026-07-24",
  "method": {
    "range": [
      -100,
      100
    ],
    "formula": "I = 100 * sum(normalized_weight_i * direction_i) / (n + 2)",
    "raw_formula": "100 * sum(direction * weight) / sum(weight), directional viewpoints only",
    "weight": "tier weight (1.5/1.2/1.0) * capped log engagement weight (1.0-2.0)",
    "weight_normalization": "directional weights are divided by their daily mean, so their sum equals n",
    "prior": "Beta(1,1) uniform prior: one bullish and one bearish pseudo-observation",
    "confidence": "n/(n+2)",
    "neutral": "views without deterministic direction are excluded from the score denominator"
  },
  "daily": [
    {
      "date": "2026-06-08",
      "source": "structured_views",
      "assets": {
        "energy": {
          "label_zh": "能源",
          "label_en": "Energy",
          "color": "#ef8f4c",
          "score": null,
          "raw_score": null,
          "confidence": 0.0,
          "status": "no_direction",
          "mentions": 1,
          "signal_tweets": 0,
          "kols": 1,
          "bullish": 0,
          "bearish": 0
        },
        "metals": {
          "label_zh": "金属",
          "label_en": "Metals",
          "color": "#d8ad55",
          "score": null,
          "raw_score": null,
          "confidence": 0.0,
          "status": "no_data",
          "mentions": 0,
          "signal_tweets": 0,
          "kols": 0,
          "bullish": 0,
          "bearish": 0
        },
        "grains": {
          "label_zh": "谷物油籽",
          "label_en": "Grains & Oilseeds",
          "color": "#76b77b",
          "score": null,
          "raw_score": null,
          "confidence": 0.0,
          "status": "no_data",
          "mentions": 0,
          "signal_tweets": 0,
          "kols": 0,
          "bullish": 0,
          "bearish": 0
        },
        "softs": {
          "label_zh": "软商品",
          "label_en": "Soft Commodities",
          "color": "#df6f91",
          "score": null,
          "raw_score": null,
          "confidence": 0.0,
          "status": "no_data",
          "mentions": 0,
          "signal_tweets": 0,
          "kols": 0,
          "bullish": 0,
          "bearish": 0
        }
      }
    },
    {
      "date": "2026-06-09",
      "source": "structured_views",
      "assets": {
        "energy": {
          "label_zh": "能源",
          "label_en": "Energy",
          "color": "#ef8f4c",
          "score": null,
          "raw_score": null,
          "confidence": 0.0,
          "status": "no_direction",
          "mentions": 2,
          "signal_tweets": 0,
          "kols": 2,
          "bullish": 0,
          "bearish": 0
        },
        "metals": {
          "label_zh": "金属",
          "label_en": "Metals",
          "color": "#d8ad55",
          "score": null,
          "raw_score": null,
          "confidence": 0.0,
          "status": "no_direction",
          "mentions": 1,
          "signal_tweets": 0,
          "kols": 1,
          "bullish": 0,
          "bearish": 0
        },
        "grains": {
          "label_zh": "谷物油籽",
          "label_en": "Grains & Oilseeds",
          "color": "#76b77b",
          "score": -33.3,
          "raw_score": -100.0,
          "confidence": 0.333,
          "status": "signal",
          "mentions": 1,
          "signal_tweets": 1,
          "kols": 1,
          "bullish": 0,
          "bearish": 1
        },
        "softs": {
          "label_zh": "软商品",
          "label_en": "Soft Commodities",
          "color": "#df6f91",
          "score": null,
          "raw_score": null,
          "confidence": 0.0,
          "status": "no_data",
          "mentions": 0,
          "signal_tweets": 0,
          "kols": 0,
          "bullish": 0,
          "bearish": 0
        }
      }
    },
    {
      "date": "2026-06-10",
      "source": "structured_views",
      "assets": {
        "energy": {
          "label_zh": "能源",
          "label_en": "Energy",
          "color": "#ef8f4c",
          "score": -50.0,
          "raw_score": -100.0,
          "confidence": 0.5,
          "status": "signal",
          "mentions": 5,
          "signal_tweets": 2,
          "kols": 5,
          "bullish": 0,
          "bearish": 2
        },
        "metals": {
          "label_zh": "金属",
          "label_en": "Metals",
          "color": "#d8ad55",
          "score": -33.3,
          "raw_score": -100.0,
          "confidence": 0.333,
          "status": "signal",
          "mentions": 2,
          "signal_tweets": 1,
          "kols": 2,
          "bullish": 0,
          "bearish": 1
        },
        "grains": {
          "label_zh": "谷物油籽",
          "label_en": "Grains & Oilseeds",
          "color": "#76b77b",
          "score": null,
          "raw_score": null,
          "confidence": 0.0,
          "status": "no_direction",
          "mentions": 1,
          "signal_tweets": 0,
          "kols": 1,
          "bullish": 0,
          "bearish": 0
        },
        "softs": {
          "label_zh": "软商品",
          "label_en": "Soft Commodities",
          "color": "#df6f91",
          "score": null,
          "raw_score": null,
          "confidence": 0.0,
          "status": "no_data",
          "mentions": 0,
          "signal_tweets": 0,
          "kols": 0,
          "bullish": 0,
          "bearish": 0
        }
      }
    },
    {
      "date": "2026-06-11",
      "source": "structured_views",
      "assets": {
        "energy": {
          "label_zh": "能源",
          "label_en": "Energy",
          "color": "#ef8f4c",
          "score": null,
          "raw_score": null,
          "confidence": 0.0,
          "status": "no_direction",
          "mentions": 3,
          "signal_tweets": 0,
          "kols": 3,
          "bullish": 0,
          "bearish": 0
        },
        "metals": {
          "label_zh": "金属",
          "label_en": "Metals",
          "color": "#d8ad55",
          "score": 33.3,
          "raw_score": 100.0,
          "confidence": 0.333,
          "status": "signal",
          "mentions": 1,
          "signal_tweets": 1,
          "kols": 1,
          "bullish": 1,
          "bearish": 0
        },
        "grains": {
          "label_zh": "谷物油籽",
          "label_en": "Grains & Oilseeds",
          "color": "#76b77b",
          "score": null,
          "raw_score": null,
          "confidence": 0.0,
          "status": "no_data",
          "mentions": 0,
          "signal_tweets": 0,
          "kols": 0,
          "bullish": 0,
          "bearish": 0
        },
        "softs": {
          "label_zh": "软商品",
          "label_en": "Soft Commodities",
          "color": "#df6f91",
          "score": null,
          "raw_score": null,
          "confidence": 0.0,
          "status": "no_data",
          "mentions": 0,
          "signal_tweets": 0,
          "kols": 0,
          "bullish": 0,
          "bearish": 0
        }
      }
    },
    {
      "date": "2026-06-12",
      "source": "structured_views",
      "assets": {
        "energy": {
          "label_zh": "能源",
          "label_en": "Energy",
          "color": "#ef8f4c",
          "score": null,
          "raw_score": null,
          "confidence": 0.0,
          "status": "no_direction",
          "mentions": 1,
          "signal_tweets": 0,
          "kols": 1,
          "bullish": 0,
          "bearish": 0
        },
        "metals": {
          "label_zh": "金属",
          "label_en": "Metals",
          "color": "#d8ad55",
          "score": -33.3,
          "raw_score": -100.0,
          "confidence": 0.333,
          "status": "signal",
          "mentions": 1,
          "signal_tweets": 1,
          "kols": 1,
          "bullish": 0,
          "bearish": 1
        },
        "grains": {
          "label_zh": "谷物油籽",
          "label_en": "Grains & Oilseeds",
          "color": "#76b77b",
          "score": 33.3,
          "raw_score": 100.0,
          "confidence": 0.333,
          "status": "signal",
          "mentions": 2,
          "signal_tweets": 1,
          "kols": 1,
          "bullish": 1,
          "bearish": 0
        },
        "softs": {
          "label_zh": "软商品",
          "label_en": "Soft Commodities",
          "color": "#df6f91",
          "score": null,
          "raw_score": null,
          "confidence": 0.0,
          "status": "no_data",
          "mentions": 0,
          "signal_tweets": 0,
          "kols": 0,
          "bullish": 0,
          "bearish": 0
        }
      }
    },
    {
      "date": "2026-06-15",
      "source": "structured_views",
      "assets": {
        "energy": {
          "label_zh": "能源",
          "label_en": "Energy",
          "color": "#ef8f4c",
          "score": 33.3,
          "raw_score": 100.0,
          "confidence": 0.333,
          "status": "signal",
          "mentions": 1,
          "signal_tweets": 1,
          "kols": 1,
          "bullish": 1,
          "bearish": 0
        },
        "metals": {
          "label_zh": "金属",
          "label_en": "Metals",
          "color": "#d8ad55",
          "score": null,
          "raw_score": null,
          "confidence": 0.0,
          "status": "no_data",
          "mentions": 0,
          "signal_tweets": 0,
          "kols": 0,
          "bullish": 0,
          "bearish": 0
        },
        "grains": {
          "label_zh": "谷物油籽",
          "label_en": "Grains & Oilseeds",
          "color": "#76b77b",
          "score": null,
          "raw_score": null,
          "confidence": 0.0,
          "status": "no_direction",
          "mentions": 1,
          "signal_tweets": 0,
          "kols": 1,
          "bullish": 0,
          "bearish": 0
        },
        "softs": {
          "label_zh": "软商品",
          "label_en": "Soft Commodities",
          "color": "#df6f91",
          "score": null,
          "raw_score": null,
          "confidence": 0.0,
          "status": "no_data",
          "mentions": 0,
          "signal_tweets": 0,
          "kols": 0,
          "bullish": 0,
          "bearish": 0
        }
      }
    },
    {
      "date": "2026-06-16",
      "source": "structured_views",
      "assets": {
        "energy": {
          "label_zh": "能源",
          "label_en": "Energy",
          "color": "#ef8f4c",
          "score": 50.0,
          "raw_score": 100.0,
          "confidence": 0.5,
          "status": "signal",
          "mentions": 2,
          "signal_tweets": 2,
          "kols": 2,
          "bullish": 2,
          "bearish": 0
        },
        "metals": {
          "label_zh": "金属",
          "label_en": "Metals",
          "color": "#d8ad55",
          "score": 33.3,
          "raw_score": 100.0,
          "confidence": 0.333,
          "status": "signal",
          "mentions": 1,
          "signal_tweets": 1,
          "kols": 1,
          "bullish": 1,
          "bearish": 0
        },
        "grains": {
          "label_zh": "谷物油籽",
          "label_en": "Grains & Oilseeds",
          "color": "#76b77b",
          "score": -33.3,
          "raw_score": -100.0,
          "confidence": 0.333,
          "status": "signal",
          "mentions": 2,
          "signal_tweets": 1,
          "kols": 2,
          "bullish": 0,
          "bearish": 1
        },
        "softs": {
          "label_zh": "软商品",
          "label_en": "Soft Commodities",
          "color": "#df6f91",
          "score": null,
          "raw_score": null,
          "confidence": 0.0,
          "status": "no_direction",
          "mentions": 1,
          "signal_tweets": 0,
          "kols": 1,
          "bullish": 0,
          "bearish": 0
        }
      }
    },
    {
      "date": "2026-06-24",
      "source": "raw_tweets",
      "assets": {
        "energy": {
          "label_zh": "能源",
          "label_en": "Energy",
          "color": "#ef8f4c",
          "score": -60.0,
          "raw_score": -100.0,
          "confidence": 0.6,
          "status": "signal",
          "mentions": 14,
          "signal_tweets": 3,
          "kols": 9,
          "bullish": 0,
          "bearish": 3
        },
        "metals": {
          "label_zh": "金属",
          "label_en": "Metals",
          "color": "#d8ad55",
          "score": -19.2,
          "raw_score": -32.0,
          "confidence": 0.6,
          "status": "signal",
          "mentions": 4,
          "signal_tweets": 3,
          "kols": 4,
          "bullish": 1,
          "bearish": 2
        },
        "grains": {
          "label_zh": "谷物油籽",
          "label_en": "Grains & Oilseeds",
          "color": "#76b77b",
          "score": null,
          "raw_score": null,
          "confidence": 0.0,
          "status": "no_direction",
          "mentions": 1,
          "signal_tweets": 0,
          "kols": 1,
          "bullish": 0,
          "bearish": 0
        },
        "softs": {
          "label_zh": "软商品",
          "label_en": "Soft Commodities",
          "color": "#df6f91",
          "score": null,
          "raw_score": null,
          "confidence": 0.0,
          "status": "no_data",
          "mentions": 0,
          "signal_tweets": 0,
          "kols": 0,
          "bullish": 0,
          "bearish": 0
        }
      }
    },
    {
      "date": "2026-06-30",
      "source": "raw_tweets",
      "assets": {
        "energy": {
          "label_zh": "能源",
          "label_en": "Energy",
          "color": "#ef8f4c",
          "score": -30.2,
          "raw_score": -37.0,
          "confidence": 0.818,
          "status": "signal",
          "mentions": 12,
          "signal_tweets": 9,
          "kols": 7,
          "bullish": 3,
          "bearish": 6
        },
        "metals": {
          "label_zh": "金属",
          "label_en": "Metals",
          "color": "#d8ad55",
          "score": null,
          "raw_score": null,
          "confidence": 0.0,
          "status": "no_direction",
          "mentions": 1,
          "signal_tweets": 0,
          "kols": 1,
          "bullish": 0,
          "bearish": 0
        },
        "grains": {
          "label_zh": "谷物油籽",
          "label_en": "Grains & Oilseeds",
          "color": "#76b77b",
          "score": 1.0,
          "raw_score": 2.0,
          "confidence": 0.5,
          "status": "signal",
          "mentions": 3,
          "signal_tweets": 2,
          "kols": 3,
          "bullish": 1,
          "bearish": 1
        },
        "softs": {
          "label_zh": "软商品",
          "label_en": "Soft Commodities",
          "color": "#df6f91",
          "score": null,
          "raw_score": null,
          "confidence": 0.0,
          "status": "no_data",
          "mentions": 0,
          "signal_tweets": 0,
          "kols": 0,
          "bullish": 0,
          "bearish": 0
        }
      }
    },
    {
      "date": "2026-07-01",
      "source": "raw_tweets",
      "assets": {
        "energy": {
          "label_zh": "能源",
          "label_en": "Energy",
          "color": "#ef8f4c",
          "score": -60.0,
          "raw_score": -100.0,
          "confidence": 0.6,
          "status": "signal",
          "mentions": 8,
          "signal_tweets": 3,
          "kols": 7,
          "bullish": 0,
          "bearish": 3
        },
        "metals": {
          "label_zh": "金属",
          "label_en": "Metals",
          "color": "#d8ad55",
          "score": -7.7,
          "raw_score": -15.4,
          "confidence": 0.5,
          "status": "signal",
          "mentions": 2,
          "signal_tweets": 2,
          "kols": 2,
          "bullish": 1,
          "bearish": 1
        },
        "grains": {
          "label_zh": "谷物油籽",
          "label_en": "Grains & Oilseeds",
          "color": "#76b77b",
          "score": 33.3,
          "raw_score": 100.0,
          "confidence": 0.333,
          "status": "signal",
          "mentions": 5,
          "signal_tweets": 1,
          "kols": 2,
          "bullish": 1,
          "bearish": 0
        },
        "softs": {
          "label_zh": "软商品",
          "label_en": "Soft Commodities",
          "color": "#df6f91",
          "score": null,
          "raw_score": null,
          "confidence": 0.0,
          "status": "no_data",
          "mentions": 0,
          "signal_tweets": 0,
          "kols": 0,
          "bullish": 0,
          "bearish": 0
        }
      }
    },
    {
      "date": "2026-07-02",
      "source": "raw_tweets",
      "assets": {
        "energy": {
          "label_zh": "能源",
          "label_en": "Energy",
          "color": "#ef8f4c",
          "score": -23.8,
          "raw_score": -35.7,
          "confidence": 0.667,
          "status": "signal",
          "mentions": 9,
          "signal_tweets": 4,
          "kols": 7,
          "bullish": 1,
          "bearish": 3
        },
        "metals": {
          "label_zh": "金属",
          "label_en": "Metals",
          "color": "#d8ad55",
          "score": 50.0,
          "raw_score": 100.0,
          "confidence": 0.5,
          "status": "signal",
          "mentions": 6,
          "signal_tweets": 2,
          "kols": 5,
          "bullish": 2,
          "bearish": 0
        },
        "grains": {
          "label_zh": "谷物油籽",
          "label_en": "Grains & Oilseeds",
          "color": "#76b77b",
          "score": null,
          "raw_score": null,
          "confidence": 0.0,
          "status": "no_data",
          "mentions": 0,
          "signal_tweets": 0,
          "kols": 0,
          "bullish": 0,
          "bearish": 0
        },
        "softs": {
          "label_zh": "软商品",
          "label_en": "Soft Commodities",
          "color": "#df6f91",
          "score": null,
          "raw_score": null,
          "confidence": 0.0,
          "status": "no_data",
          "mentions": 0,
          "signal_tweets": 0,
          "kols": 0,
          "bullish": 0,
          "bearish": 0
        }
      }
    },
    {
      "date": "2026-07-03",
      "source": "raw_tweets",
      "assets": {
        "energy": {
          "label_zh": "能源",
          "label_en": "Energy",
          "color": "#ef8f4c",
          "score": -48.0,
          "raw_score": -63.9,
          "confidence": 0.75,
          "status": "signal",
          "mentions": 8,
          "signal_tweets": 6,
          "kols": 5,
          "bullish": 1,
          "bearish": 5
        },
        "metals": {
          "label_zh": "金属",
          "label_en": "Metals",
          "color": "#d8ad55",
          "score": 2.3,
          "raw_score": 4.6,
          "confidence": 0.5,
          "status": "signal",
          "mentions": 3,
          "signal_tweets": 2,
          "kols": 3,
          "bullish": 1,
          "bearish": 1
        },
        "grains": {
          "label_zh": "谷物油籽",
          "label_en": "Grains & Oilseeds",
          "color": "#76b77b",
          "score": null,
          "raw_score": null,
          "confidence": 0.0,
          "status": "no_direction",
          "mentions": 1,
          "signal_tweets": 0,
          "kols": 1,
          "bullish": 0,
          "bearish": 0
        },
        "softs": {
          "label_zh": "软商品",
          "label_en": "Soft Commodities",
          "color": "#df6f91",
          "score": null,
          "raw_score": null,
          "confidence": 0.0,
          "status": "no_data",
          "mentions": 0,
          "signal_tweets": 0,
          "kols": 0,
          "bullish": 0,
          "bearish": 0
        }
      }
    },
    {
      "date": "2026-07-06",
      "source": "raw_tweets",
      "assets": {
        "energy": {
          "label_zh": "能源",
          "label_en": "Energy",
          "color": "#ef8f4c",
          "score": 3.2,
          "raw_score": 6.4,
          "confidence": 0.5,
          "status": "signal",
          "mentions": 9,
          "signal_tweets": 2,
          "kols": 6,
          "bullish": 1,
          "bearish": 1
        },
        "metals": {
          "label_zh": "金属",
          "label_en": "Metals",
          "color": "#d8ad55",
          "score": null,
          "raw_score": null,
          "confidence": 0.0,
          "status": "no_direction",
          "mentions": 1,
          "signal_tweets": 0,
          "kols": 1,
          "bullish": 0,
          "bearish": 0
        },
        "grains": {
          "label_zh": "谷物油籽",
          "label_en": "Grains & Oilseeds",
          "color": "#76b77b",
          "score": null,
          "raw_score": null,
          "confidence": 0.0,
          "status": "no_data",
          "mentions": 0,
          "signal_tweets": 0,
          "kols": 0,
          "bullish": 0,
          "bearish": 0
        },
        "softs": {
          "label_zh": "软商品",
          "label_en": "Soft Commodities",
          "color": "#df6f91",
          "score": null,
          "raw_score": null,
          "confidence": 0.0,
          "status": "no_data",
          "mentions": 0,
          "signal_tweets": 0,
          "kols": 0,
          "bullish": 0,
          "bearish": 0
        }
      }
    },
    {
      "date": "2026-07-07",
      "source": "raw_tweets",
      "assets": {
        "energy": {
          "label_zh": "能源",
          "label_en": "Energy",
          "color": "#ef8f4c",
          "score": null,
          "raw_score": null,
          "confidence": 0.0,
          "status": "no_direction",
          "mentions": 1,
          "signal_tweets": 0,
          "kols": 1,
          "bullish": 0,
          "bearish": 0
        },
        "metals": {
          "label_zh": "金属",
          "label_en": "Metals",
          "color": "#d8ad55",
          "score": null,
          "raw_score": null,
          "confidence": 0.0,
          "status": "no_direction",
          "mentions": 1,
          "signal_tweets": 0,
          "kols": 1,
          "bullish": 0,
          "bearish": 0
        },
        "grains": {
          "label_zh": "谷物油籽",
          "label_en": "Grains & Oilseeds",
          "color": "#76b77b",
          "score": null,
          "raw_score": null,
          "confidence": 0.0,
          "status": "no_data",
          "mentions": 0,
          "signal_tweets": 0,
          "kols": 0,
          "bullish": 0,
          "bearish": 0
        },
        "softs": {
          "label_zh": "软商品",
          "label_en": "Soft Commodities",
          "color": "#df6f91",
          "score": null,
          "raw_score": null,
          "confidence": 0.0,
          "status": "no_data",
          "mentions": 0,
          "signal_tweets": 0,
          "kols": 0,
          "bullish": 0,
          "bearish": 0
        }
      }
    },
    {
      "date": "2026-07-08",
      "source": "structured_views",
      "assets": {
        "energy": {
          "label_zh": "能源",
          "label_en": "Energy",
          "color": "#ef8f4c",
          "score": 33.3,
          "raw_score": 100.0,
          "confidence": 0.333,
          "status": "signal",
          "mentions": 2,
          "signal_tweets": 1,
          "kols": 2,
          "bullish": 1,
          "bearish": 0
        },
        "metals": {
          "label_zh": "金属",
          "label_en": "Metals",
          "color": "#d8ad55",
          "score": null,
          "raw_score": null,
          "confidence": 0.0,
          "status": "no_direction",
          "mentions": 1,
          "signal_tweets": 0,
          "kols": 1,
          "bullish": 0,
          "bearish": 0
        },
        "grains": {
          "label_zh": "谷物油籽",
          "label_en": "Grains & Oilseeds",
          "color": "#76b77b",
          "score": null,
          "raw_score": null,
          "confidence": 0.0,
          "status": "no_data",
          "mentions": 0,
          "signal_tweets": 0,
          "kols": 0,
          "bullish": 0,
          "bearish": 0
        },
        "softs": {
          "label_zh": "软商品",
          "label_en": "Soft Commodities",
          "color": "#df6f91",
          "score": null,
          "raw_score": null,
          "confidence": 0.0,
          "status": "no_data",
          "mentions": 0,
          "signal_tweets": 0,
          "kols": 0,
          "bullish": 0,
          "bearish": 0
        }
      }
    },
    {
      "date": "2026-07-09",
      "source": "structured_views",
      "assets": {
        "energy": {
          "label_zh": "能源",
          "label_en": "Energy",
          "color": "#ef8f4c",
          "score": 33.3,
          "raw_score": 100.0,
          "confidence": 0.333,
          "status": "signal",
          "mentions": 3,
          "signal_tweets": 1,
          "kols": 3,
          "bullish": 1,
          "bearish": 0
        },
        "metals": {
          "label_zh": "金属",
          "label_en": "Metals",
          "color": "#d8ad55",
          "score": null,
          "raw_score": null,
          "confidence": 0.0,
          "status": "no_direction",
          "mentions": 1,
          "signal_tweets": 0,
          "kols": 1,
          "bullish": 0,
          "bearish": 0
        },
        "grains": {
          "label_zh": "谷物油籽",
          "label_en": "Grains & Oilseeds",
          "color": "#76b77b",
          "score": null,
          "raw_score": null,
          "confidence": 0.0,
          "status": "no_data",
          "mentions": 0,
          "signal_tweets": 0,
          "kols": 0,
          "bullish": 0,
          "bearish": 0
        },
        "softs": {
          "label_zh": "软商品",
          "label_en": "Soft Commodities",
          "color": "#df6f91",
          "score": null,
          "raw_score": null,
          "confidence": 0.0,
          "status": "no_data",
          "mentions": 0,
          "signal_tweets": 0,
          "kols": 0,
          "bullish": 0,
          "bearish": 0
        }
      }
    },
    {
      "date": "2026-07-10",
      "source": "structured_views",
      "assets": {
        "energy": {
          "label_zh": "能源",
          "label_en": "Energy",
          "color": "#ef8f4c",
          "score": null,
          "raw_score": null,
          "confidence": 0.0,
          "status": "no_data",
          "mentions": 0,
          "signal_tweets": 0,
          "kols": 0,
          "bullish": 0,
          "bearish": 0
        },
        "metals": {
          "label_zh": "金属",
          "label_en": "Metals",
          "color": "#d8ad55",
          "score": null,
          "raw_score": null,
          "confidence": 0.0,
          "status": "no_direction",
          "mentions": 1,
          "signal_tweets": 0,
          "kols": 1,
          "bullish": 0,
          "bearish": 0
        },
        "grains": {
          "label_zh": "谷物油籽",
          "label_en": "Grains & Oilseeds",
          "color": "#76b77b",
          "score": null,
          "raw_score": null,
          "confidence": 0.0,
          "status": "no_data",
          "mentions": 0,
          "signal_tweets": 0,
          "kols": 0,
          "bullish": 0,
          "bearish": 0
        },
        "softs": {
          "label_zh": "软商品",
          "label_en": "Soft Commodities",
          "color": "#df6f91",
          "score": null,
          "raw_score": null,
          "confidence": 0.0,
          "status": "no_data",
          "mentions": 0,
          "signal_tweets": 0,
          "kols": 0,
          "bullish": 0,
          "bearish": 0
        }
      }
    },
    {
      "date": "2026-07-11",
      "source": "structured_views",
      "assets": {
        "energy": {
          "label_zh": "能源",
          "label_en": "Energy",
          "color": "#ef8f4c",
          "score": null,
          "raw_score": null,
          "confidence": 0.0,
          "status": "no_data",
          "mentions": 0,
          "signal_tweets": 0,
          "kols": 0,
          "bullish": 0,
          "bearish": 0
        },
        "metals": {
          "label_zh": "金属",
          "label_en": "Metals",
          "color": "#d8ad55",
          "score": 33.3,
          "raw_score": 100.0,
          "confidence": 0.333,
          "status": "signal",
          "mentions": 1,
          "signal_tweets": 1,
          "kols": 1,
          "bullish": 1,
          "bearish": 0
        },
        "grains": {
          "label_zh": "谷物油籽",
          "label_en": "Grains & Oilseeds",
          "color": "#76b77b",
          "score": null,
          "raw_score": null,
          "confidence": 0.0,
          "status": "no_data",
          "mentions": 0,
          "signal_tweets": 0,
          "kols": 0,
          "bullish": 0,
          "bearish": 0
        },
        "softs": {
          "label_zh": "软商品",
          "label_en": "Soft Commodities",
          "color": "#df6f91",
          "score": null,
          "raw_score": null,
          "confidence": 0.0,
          "status": "no_data",
          "mentions": 0,
          "signal_tweets": 0,
          "kols": 0,
          "bullish": 0,
          "bearish": 0
        }
      }
    },
    {
      "date": "2026-07-12",
      "source": "structured_views",
      "assets": {
        "energy": {
          "label_zh": "能源",
          "label_en": "Energy",
          "color": "#ef8f4c",
          "score": null,
          "raw_score": null,
          "confidence": 0.0,
          "status": "no_data",
          "mentions": 0,
          "signal_tweets": 0,
          "kols": 0,
          "bullish": 0,
          "bearish": 0
        },
        "metals": {
          "label_zh": "金属",
          "label_en": "Metals",
          "color": "#d8ad55",
          "score": null,
          "raw_score": null,
          "confidence": 0.0,
          "status": "no_data",
          "mentions": 0,
          "signal_tweets": 0,
          "kols": 0,
          "bullish": 0,
          "bearish": 0
        },
        "grains": {
          "label_zh": "谷物油籽",
          "label_en": "Grains & Oilseeds",
          "color": "#76b77b",
          "score": null,
          "raw_score": null,
          "confidence": 0.0,
          "status": "no_data",
          "mentions": 0,
          "signal_tweets": 0,
          "kols": 0,
          "bullish": 0,
          "bearish": 0
        },
        "softs": {
          "label_zh": "软商品",
          "label_en": "Soft Commodities",
          "color": "#df6f91",
          "score": null,
          "raw_score": null,
          "confidence": 0.0,
          "status": "no_data",
          "mentions": 0,
          "signal_tweets": 0,
          "kols": 0,
          "bullish": 0,
          "bearish": 0
        }
      }
    },
    {
      "date": "2026-07-13",
      "source": "structured_views",
      "assets": {
        "energy": {
          "label_zh": "能源",
          "label_en": "Energy",
          "color": "#ef8f4c",
          "score": null,
          "raw_score": null,
          "confidence": 0.0,
          "status": "no_data",
          "mentions": 0,
          "signal_tweets": 0,
          "kols": 0,
          "bullish": 0,
          "bearish": 0
        },
        "metals": {
          "label_zh": "金属",
          "label_en": "Metals",
          "color": "#d8ad55",
          "score": null,
          "raw_score": null,
          "confidence": 0.0,
          "status": "no_data",
          "mentions": 0,
          "signal_tweets": 0,
          "kols": 0,
          "bullish": 0,
          "bearish": 0
        },
        "grains": {
          "label_zh": "谷物油籽",
          "label_en": "Grains & Oilseeds",
          "color": "#76b77b",
          "score": null,
          "raw_score": null,
          "confidence": 0.0,
          "status": "no_data",
          "mentions": 0,
          "signal_tweets": 0,
          "kols": 0,
          "bullish": 0,
          "bearish": 0
        },
        "softs": {
          "label_zh": "软商品",
          "label_en": "Soft Commodities",
          "color": "#df6f91",
          "score": null,
          "raw_score": null,
          "confidence": 0.0,
          "status": "no_data",
          "mentions": 0,
          "signal_tweets": 0,
          "kols": 0,
          "bullish": 0,
          "bearish": 0
        }
      }
    },
    {
      "date": "2026-07-14",
      "source": "structured_views",
      "assets": {
        "energy": {
          "label_zh": "能源",
          "label_en": "Energy",
          "color": "#ef8f4c",
          "score": null,
          "raw_score": null,
          "confidence": 0.0,
          "status": "no_data",
          "mentions": 0,
          "signal_tweets": 0,
          "kols": 0,
          "bullish": 0,
          "bearish": 0
        },
        "metals": {
          "label_zh": "金属",
          "label_en": "Metals",
          "color": "#d8ad55",
          "score": null,
          "raw_score": null,
          "confidence": 0.0,
          "status": "no_direction",
          "mentions": 1,
          "signal_tweets": 0,
          "kols": 1,
          "bullish": 0,
          "bearish": 0
        },
        "grains": {
          "label_zh": "谷物油籽",
          "label_en": "Grains & Oilseeds",
          "color": "#76b77b",
          "score": null,
          "raw_score": null,
          "confidence": 0.0,
          "status": "no_data",
          "mentions": 0,
          "signal_tweets": 0,
          "kols": 0,
          "bullish": 0,
          "bearish": 0
        },
        "softs": {
          "label_zh": "软商品",
          "label_en": "Soft Commodities",
          "color": "#df6f91",
          "score": null,
          "raw_score": null,
          "confidence": 0.0,
          "status": "no_data",
          "mentions": 0,
          "signal_tweets": 0,
          "kols": 0,
          "bullish": 0,
          "bearish": 0
        }
      }
    },
    {
      "date": "2026-07-15",
      "source": "structured_views",
      "assets": {
        "energy": {
          "label_zh": "能源",
          "label_en": "Energy",
          "color": "#ef8f4c",
          "score": null,
          "raw_score": null,
          "confidence": 0.0,
          "status": "no_data",
          "mentions": 0,
          "signal_tweets": 0,
          "kols": 0,
          "bullish": 0,
          "bearish": 0
        },
        "metals": {
          "label_zh": "金属",
          "label_en": "Metals",
          "color": "#d8ad55",
          "score": 33.3,
          "raw_score": 100.0,
          "confidence": 0.333,
          "status": "signal",
          "mentions": 3,
          "signal_tweets": 1,
          "kols": 3,
          "bullish": 1,
          "bearish": 0
        },
        "grains": {
          "label_zh": "谷物油籽",
          "label_en": "Grains & Oilseeds",
          "color": "#76b77b",
          "score": null,
          "raw_score": null,
          "confidence": 0.0,
          "status": "no_data",
          "mentions": 0,
          "signal_tweets": 0,
          "kols": 0,
          "bullish": 0,
          "bearish": 0
        },
        "softs": {
          "label_zh": "软商品",
          "label_en": "Soft Commodities",
          "color": "#df6f91",
          "score": null,
          "raw_score": null,
          "confidence": 0.0,
          "status": "no_data",
          "mentions": 0,
          "signal_tweets": 0,
          "kols": 0,
          "bullish": 0,
          "bearish": 0
        }
      }
    },
    {
      "date": "2026-07-16",
      "source": "structured_views",
      "assets": {
        "energy": {
          "label_zh": "能源",
          "label_en": "Energy",
          "color": "#ef8f4c",
          "score": null,
          "raw_score": null,
          "confidence": 0.0,
          "status": "no_direction",
          "mentions": 1,
          "signal_tweets": 0,
          "kols": 1,
          "bullish": 0,
          "bearish": 0
        },
        "metals": {
          "label_zh": "金属",
          "label_en": "Metals",
          "color": "#d8ad55",
          "score": null,
          "raw_score": null,
          "confidence": 0.0,
          "status": "no_data",
          "mentions": 0,
          "signal_tweets": 0,
          "kols": 0,
          "bullish": 0,
          "bearish": 0
        },
        "grains": {
          "label_zh": "谷物油籽",
          "label_en": "Grains & Oilseeds",
          "color": "#76b77b",
          "score": null,
          "raw_score": null,
          "confidence": 0.0,
          "status": "no_data",
          "mentions": 0,
          "signal_tweets": 0,
          "kols": 0,
          "bullish": 0,
          "bearish": 0
        },
        "softs": {
          "label_zh": "软商品",
          "label_en": "Soft Commodities",
          "color": "#df6f91",
          "score": null,
          "raw_score": null,
          "confidence": 0.0,
          "status": "no_data",
          "mentions": 0,
          "signal_tweets": 0,
          "kols": 0,
          "bullish": 0,
          "bearish": 0
        }
      }
    },
    {
      "date": "2026-07-17",
      "source": "structured_views",
      "assets": {
        "energy": {
          "label_zh": "能源",
          "label_en": "Energy",
          "color": "#ef8f4c",
          "score": 33.3,
          "raw_score": 100.0,
          "confidence": 0.333,
          "status": "signal",
          "mentions": 1,
          "signal_tweets": 1,
          "kols": 1,
          "bullish": 1,
          "bearish": 0
        },
        "metals": {
          "label_zh": "金属",
          "label_en": "Metals",
          "color": "#d8ad55",
          "score": 33.3,
          "raw_score": 100.0,
          "confidence": 0.333,
          "status": "signal",
          "mentions": 1,
          "signal_tweets": 1,
          "kols": 1,
          "bullish": 1,
          "bearish": 0
        },
        "grains": {
          "label_zh": "谷物油籽",
          "label_en": "Grains & Oilseeds",
          "color": "#76b77b",
          "score": null,
          "raw_score": null,
          "confidence": 0.0,
          "status": "no_data",
          "mentions": 0,
          "signal_tweets": 0,
          "kols": 0,
          "bullish": 0,
          "bearish": 0
        },
        "softs": {
          "label_zh": "软商品",
          "label_en": "Soft Commodities",
          "color": "#df6f91",
          "score": null,
          "raw_score": null,
          "confidence": 0.0,
          "status": "no_data",
          "mentions": 0,
          "signal_tweets": 0,
          "kols": 0,
          "bullish": 0,
          "bearish": 0
        }
      }
    },
    {
      "date": "2026-07-18",
      "source": "structured_views",
      "assets": {
        "energy": {
          "label_zh": "能源",
          "label_en": "Energy",
          "color": "#ef8f4c",
          "score": null,
          "raw_score": null,
          "confidence": 0.0,
          "status": "no_data",
          "mentions": 0,
          "signal_tweets": 0,
          "kols": 0,
          "bullish": 0,
          "bearish": 0
        },
        "metals": {
          "label_zh": "金属",
          "label_en": "Metals",
          "color": "#d8ad55",
          "score": null,
          "raw_score": null,
          "confidence": 0.0,
          "status": "no_data",
          "mentions": 0,
          "signal_tweets": 0,
          "kols": 0,
          "bullish": 0,
          "bearish": 0
        },
        "grains": {
          "label_zh": "谷物油籽",
          "label_en": "Grains & Oilseeds",
          "color": "#76b77b",
          "score": null,
          "raw_score": null,
          "confidence": 0.0,
          "status": "no_data",
          "mentions": 0,
          "signal_tweets": 0,
          "kols": 0,
          "bullish": 0,
          "bearish": 0
        },
        "softs": {
          "label_zh": "软商品",
          "label_en": "Soft Commodities",
          "color": "#df6f91",
          "score": null,
          "raw_score": null,
          "confidence": 0.0,
          "status": "no_data",
          "mentions": 0,
          "signal_tweets": 0,
          "kols": 0,
          "bullish": 0,
          "bearish": 0
        }
      }
    },
    {
      "date": "2026-07-19",
      "source": "structured_views",
      "assets": {
        "energy": {
          "label_zh": "能源",
          "label_en": "Energy",
          "color": "#ef8f4c",
          "score": null,
          "raw_score": null,
          "confidence": 0.0,
          "status": "no_data",
          "mentions": 0,
          "signal_tweets": 0,
          "kols": 0,
          "bullish": 0,
          "bearish": 0
        },
        "metals": {
          "label_zh": "金属",
          "label_en": "Metals",
          "color": "#d8ad55",
          "score": null,
          "raw_score": null,
          "confidence": 0.0,
          "status": "no_data",
          "mentions": 0,
          "signal_tweets": 0,
          "kols": 0,
          "bullish": 0,
          "bearish": 0
        },
        "grains": {
          "label_zh": "谷物油籽",
          "label_en": "Grains & Oilseeds",
          "color": "#76b77b",
          "score": null,
          "raw_score": null,
          "confidence": 0.0,
          "status": "no_data",
          "mentions": 0,
          "signal_tweets": 0,
          "kols": 0,
          "bullish": 0,
          "bearish": 0
        },
        "softs": {
          "label_zh": "软商品",
          "label_en": "Soft Commodities",
          "color": "#df6f91",
          "score": null,
          "raw_score": null,
          "confidence": 0.0,
          "status": "no_data",
          "mentions": 0,
          "signal_tweets": 0,
          "kols": 0,
          "bullish": 0,
          "bearish": 0
        }
      }
    },
    {
      "date": "2026-07-20",
      "source": "structured_views",
      "assets": {
        "energy": {
          "label_zh": "能源",
          "label_en": "Energy",
          "color": "#ef8f4c",
          "score": 33.3,
          "raw_score": 100.0,
          "confidence": 0.333,
          "status": "signal",
          "mentions": 1,
          "signal_tweets": 1,
          "kols": 1,
          "bullish": 1,
          "bearish": 0
        },
        "metals": {
          "label_zh": "金属",
          "label_en": "Metals",
          "color": "#d8ad55",
          "score": null,
          "raw_score": null,
          "confidence": 0.0,
          "status": "no_data",
          "mentions": 0,
          "signal_tweets": 0,
          "kols": 0,
          "bullish": 0,
          "bearish": 0
        },
        "grains": {
          "label_zh": "谷物油籽",
          "label_en": "Grains & Oilseeds",
          "color": "#76b77b",
          "score": null,
          "raw_score": null,
          "confidence": 0.0,
          "status": "no_data",
          "mentions": 0,
          "signal_tweets": 0,
          "kols": 0,
          "bullish": 0,
          "bearish": 0
        },
        "softs": {
          "label_zh": "软商品",
          "label_en": "Soft Commodities",
          "color": "#df6f91",
          "score": null,
          "raw_score": null,
          "confidence": 0.0,
          "status": "no_data",
          "mentions": 0,
          "signal_tweets": 0,
          "kols": 0,
          "bullish": 0,
          "bearish": 0
        }
      }
    },
    {
      "date": "2026-07-21",
      "source": "structured_views",
      "assets": {
        "energy": {
          "label_zh": "能源",
          "label_en": "Energy",
          "color": "#ef8f4c",
          "score": -33.3,
          "raw_score": -100.0,
          "confidence": 0.333,
          "status": "signal",
          "mentions": 2,
          "signal_tweets": 1,
          "kols": 2,
          "bullish": 0,
          "bearish": 1
        },
        "metals": {
          "label_zh": "金属",
          "label_en": "Metals",
          "color": "#d8ad55",
          "score": 33.3,
          "raw_score": 100.0,
          "confidence": 0.333,
          "status": "signal",
          "mentions": 1,
          "signal_tweets": 1,
          "kols": 1,
          "bullish": 1,
          "bearish": 0
        },
        "grains": {
          "label_zh": "谷物油籽",
          "label_en": "Grains & Oilseeds",
          "color": "#76b77b",
          "score": 33.3,
          "raw_score": 100.0,
          "confidence": 0.333,
          "status": "signal",
          "mentions": 1,
          "signal_tweets": 1,
          "kols": 1,
          "bullish": 1,
          "bearish": 0
        },
        "softs": {
          "label_zh": "软商品",
          "label_en": "Soft Commodities",
          "color": "#df6f91",
          "score": null,
          "raw_score": null,
          "confidence": 0.0,
          "status": "no_data",
          "mentions": 0,
          "signal_tweets": 0,
          "kols": 0,
          "bullish": 0,
          "bearish": 0
        }
      }
    },
    {
      "date": "2026-07-22",
      "source": "structured_views",
      "assets": {
        "energy": {
          "label_zh": "能源",
          "label_en": "Energy",
          "color": "#ef8f4c",
          "score": null,
          "raw_score": null,
          "confidence": 0.0,
          "status": "no_direction",
          "mentions": 1,
          "signal_tweets": 0,
          "kols": 1,
          "bullish": 0,
          "bearish": 0
        },
        "metals": {
          "label_zh": "金属",
          "label_en": "Metals",
          "color": "#d8ad55",
          "score": null,
          "raw_score": null,
          "confidence": 0.0,
          "status": "no_data",
          "mentions": 0,
          "signal_tweets": 0,
          "kols": 0,
          "bullish": 0,
          "bearish": 0
        },
        "grains": {
          "label_zh": "谷物油籽",
          "label_en": "Grains & Oilseeds",
          "color": "#76b77b",
          "score": null,
          "raw_score": null,
          "confidence": 0.0,
          "status": "no_data",
          "mentions": 0,
          "signal_tweets": 0,
          "kols": 0,
          "bullish": 0,
          "bearish": 0
        },
        "softs": {
          "label_zh": "软商品",
          "label_en": "Soft Commodities",
          "color": "#df6f91",
          "score": null,
          "raw_score": null,
          "confidence": 0.0,
          "status": "no_data",
          "mentions": 0,
          "signal_tweets": 0,
          "kols": 0,
          "bullish": 0,
          "bearish": 0
        }
      }
    },
    {
      "date": "2026-07-23",
      "source": "structured_views",
      "assets": {
        "energy": {
          "label_zh": "能源",
          "label_en": "Energy",
          "color": "#ef8f4c",
          "score": null,
          "raw_score": null,
          "confidence": 0.0,
          "status": "no_direction",
          "mentions": 1,
          "signal_tweets": 0,
          "kols": 1,
          "bullish": 0,
          "bearish": 0
        },
        "metals": {
          "label_zh": "金属",
          "label_en": "Metals",
          "color": "#d8ad55",
          "score": null,
          "raw_score": null,
          "confidence": 0.0,
          "status": "no_data",
          "mentions": 0,
          "signal_tweets": 0,
          "kols": 0,
          "bullish": 0,
          "bearish": 0
        },
        "grains": {
          "label_zh": "谷物油籽",
          "label_en": "Grains & Oilseeds",
          "color": "#76b77b",
          "score": null,
          "raw_score": null,
          "confidence": 0.0,
          "status": "no_data",
          "mentions": 0,
          "signal_tweets": 0,
          "kols": 0,
          "bullish": 0,
          "bearish": 0
        },
        "softs": {
          "label_zh": "软商品",
          "label_en": "Soft Commodities",
          "color": "#df6f91",
          "score": null,
          "raw_score": null,
          "confidence": 0.0,
          "status": "no_data",
          "mentions": 0,
          "signal_tweets": 0,
          "kols": 0,
          "bullish": 0,
          "bearish": 0
        }
      }
    },
    {
      "date": "2026-07-24",
      "source": "structured_views",
      "assets": {
        "energy": {
          "label_zh": "能源",
          "label_en": "Energy",
          "color": "#ef8f4c",
          "score": 50.0,
          "raw_score": 100.0,
          "confidence": 0.5,
          "status": "signal",
          "mentions": 2,
          "signal_tweets": 2,
          "kols": 2,
          "bullish": 2,
          "bearish": 0
        },
        "metals": {
          "label_zh": "金属",
          "label_en": "Metals",
          "color": "#d8ad55",
          "score": null,
          "raw_score": null,
          "confidence": 0.0,
          "status": "no_data",
          "mentions": 0,
          "signal_tweets": 0,
          "kols": 0,
          "bullish": 0,
          "bearish": 0
        },
        "grains": {
          "label_zh": "谷物油籽",
          "label_en": "Grains & Oilseeds",
          "color": "#76b77b",
          "score": null,
          "raw_score": null,
          "confidence": 0.0,
          "status": "no_data",
          "mentions": 0,
          "signal_tweets": 0,
          "kols": 0,
          "bullish": 0,
          "bearish": 0
        },
        "softs": {
          "label_zh": "软商品",
          "label_en": "Soft Commodities",
          "color": "#df6f91",
          "score": null,
          "raw_score": null,
          "confidence": 0.0,
          "status": "no_data",
          "mentions": 0,
          "signal_tweets": 0,
          "kols": 0,
          "bullish": 0,
          "bearish": 0
        }
      }
    }
  ]
}